symboliks_json
