Metadata-Version: 2.1
Name: symboliks-json
Version: 0.0.6
Summary: Step by step solutions for symboliks
Home-page: UNKNOWN
Author: iapetos1918
Author-email: 
License: UNKNOWN
Platform: UNKNOWN
Classifier: Programming Language :: Python :: 3
Classifier: License :: OSI Approved :: MIT License
Classifier: Operating System :: OS Independent
Requires-Python: >=3.6
